todoism/__init__.py
todoism/__main__.py
todoism/backup.py
todoism/category.py
todoism/cli.py
todoism/command.py
todoism/due.py
todoism/edit.py
todoism/keycode.py
todoism/main.py
todoism/message.py
todoism/navigate.py
todoism/preference.py
todoism/print.py
todoism/safe.py
todoism/search.py
todoism/state.py
todoism/task.py
todoism/theme.py
todoism/update.py
todoism-1.21.9.post3.dist-info/licenses/LICENSE
todoism-1.21.9.post3.dist-info/METADATA
todoism-1.21.9.post3.dist-info/WHEEL
todoism-1.21.9.post3.dist-info/entry_points.txt
todoism-1.21.9.post3.dist-info/top_level.txt
todoism-1.21.9.post3.dist-info/RECORD
