Metadata-Version: 2.4
Name: todoism
Version: 1.21.9.post3
Summary: A powerful yet easy-to-use todo TUI
Author-email: Qichen Liu <liuqichne@email.com>
License: MIT
Project-URL: Homepage, https://github.com/Q1CHENL/todoism
Project-URL: BugTracker, https://github.com/Q1CHENL/todoism/issues
Classifier: Programming Language :: Python :: 3
Classifier: License :: OSI Approved :: MIT License
Classifier: Operating System :: OS Independent
Classifier: Environment :: Console
Classifier: Topic :: Utilities
Requires-Python: >=3.9
License-File: LICENSE
Dynamic: license-file
